Metadata-Version: 2.1
Name: fuel-efficiency-pathfinder
Version: 0.0.1
Summary: A package for finding fuel-efficient paths
Home-page: https://github.com/arthurcbaia/desafio-bees
Author: Arthur
Author-email: arthurceminbaia@gmail.com
